{"resourceType":"ValueSet","id":"jp-observation-socialhistory-code-vs","text":{"status":"generated","div":"<div xmlns=\"http://www.w3.org/1999/xhtml\"><ul><li>Include all codes defined in <code>http://jpfhir.jp/fhir/core/CodeSystem/JP_ObservationSocialHistoryCode_CS</code></li></ul></div>"},"url":"http://jpfhir.jp/fhir/core/ValueSet/JP_ObservationSocialHistoryCode_VS","version":"1.1.1","name":"JP_ObservationSocialHistoryCode_VS","title":"JP Core Observation SocialHistory Code ValueSet","status":"active","experimental":false,"date":"2022-10-24","publisher":"FHIR Japanese implementation research working group in Japan Association of Medical Informatics (JAMI)","contact":[{"name":"FHIR Japanese implementation research working group in Japan Association of Medical Informatics (JAMI)","telecom":[{"system":"url","value":"http://jpfhir.jp"},{"system":"email","value":"office@hlfhir.jp"}]}],"description":"Observation（生活背景）で使用する項目の値セット","jurisdiction":[{"coding":[{"system":"urn:iso:std:iso:3166","code":"JP"}]}],"copyright":"Copyright MEDIS-DC 医療情報システム開発センター","compose":{"include":[{"system":"http://jpfhir.jp/fhir/core/CodeSystem/JP_ObservationSocialHistoryCode_CS"}]}}